hoversearch/__init__.py
hoversearch/hov.py
hoversearch-0.0.6.dist-info/METADATA
hoversearch-0.0.6.dist-info/WHEEL
hoversearch-0.0.6.dist-info/top_level.txt
hoversearch-0.0.6.dist-info/RECORD
