Metadata-Version: 2.1
Name: hoversearch
Version: 0.0.6
Summary: An Youtube Video Downloader for Discord.py
Home-page: https://github.com/Miguel-cyber/hoversearch
Author: Miguel_Rose
Author-email: michaeljamesrose@outlook.com
License: UNKNOWN
Platform: UNKNOWN
Classifier: Programming Language :: Python :: 3
Classifier: License :: OSI Approved :: MIT License
Classifier: Operating System :: OS Independent
Requires-Python: >=3.6
Requires-Dist: aiohttp
Requires-Dist: pafy
Requires-Dist: Pillow
Requires-Dist: discord
Requires-Dist: beautifulsoup4
Requires-Dist: requests
Requires-Dist: youtube-dl
